github_terraform_import/__init__.py
github_terraform_import/formatter.py
github_terraform_import/importer.py
github_terraform_import/test.py
github_terraform_import/util.py
github_terraform_import/visitor.py
github_terraform_import/github_types/__init__.py
github_terraform_import/github_types/github_actions_secret.py
github_terraform_import/github_types/github_branch_protection.py
github_terraform_import/github_types/github_issue_label.py
github_terraform_import/github_types/github_membership.py
github_terraform_import/github_types/github_organization_block.py
github_terraform_import/github_types/github_organization_project.py
github_terraform_import/github_types/github_organization_webhook.py
github_terraform_import/github_types/github_project_column.py
github_terraform_import/github_types/github_repository.py
github_terraform_import/github_types/github_repository_collaborator.py
github_terraform_import/github_types/github_repository_deploy_key.py
github_terraform_import/github_types/github_repository_project.py
github_terraform_import/github_types/github_repository_webhook.py
github_terraform_import/github_types/github_team.py
github_terraform_import/github_types/github_team_membership.py
github_terraform_import/github_types/github_team_repository.py
github_terraform_import/github_types/shared.py
github_terraform_import/github_types/terraform_types.py
github_terraform_import/provider/__init__.py
github_terraform_import/provider/loader.py
github_terraform_import/provider/provider.py
github_terraform_import/provider/unwrapper.py
github_terraform_import-0.0.1.dist-info/METADATA
github_terraform_import-0.0.1.dist-info/WHEEL
github_terraform_import-0.0.1.dist-info/top_level.txt
github_terraform_import-0.0.1.dist-info/RECORD
