Metadata-Version: 2.1
Name: github-terraform-import
Version: 0.0.1
Summary: Import or sync existing Github infrastructure into terraform
Home-page: https://github.com/BraeWebb/github-terraform-import
Author: Brae Webb
Author-email: email@braewebb.com
License: MIT
Platform: UNKNOWN
Classifier: Programming Language :: Python :: 3
Classifier: Programming Language :: Python :: 3.7
Requires-Dist: requests (>=2.0)
